pygcgopt/consclassifier.pxi
pygcgopt/decomposition.pxi
pygcgopt/detector.pxi
pygcgopt/detprobdata.pxi
pygcgopt/gcg.cp313-win_amd64.pyd
pygcgopt/gcg.pxd
pygcgopt/gcg.pyx
pygcgopt/partition.pxi
pygcgopt/pricing_solver.pxi
pygcgopt/score.pxi
pygcgopt/util.py
pygcgopt/varclassifier.pxi
pygcgopt/__init__.py
PyGCGOpt-0.4.0.dist-info/DELVEWHEEL
PyGCGOpt-0.4.0.dist-info/LICENSE
PyGCGOpt-0.4.0.dist-info/METADATA
PyGCGOpt-0.4.0.dist-info/RECORD
PyGCGOpt-0.4.0.dist-info/top_level.txt
PyGCGOpt-0.4.0.dist-info/WHEEL
PyGCGOpt.libs/coinmumps-3-bcd22ed138b3de204cac30b3f877412b.dll
PyGCGOpt.libs/ipopt-3-82cb55838dd9382564638c0ef648b99a.dll
PyGCGOpt.libs/libgcg-04349ae0532d4eab8ed755b52e610adc.dll
PyGCGOpt.libs/libifcoremd-ac4eb819b7bfee486dec745d95aee235.dll
PyGCGOpt.libs/libiomp5md-8c153723f42ea6c28892c83e87529175.dll
PyGCGOpt.libs/libmmd-1ee8224c1444e721270ab90b2fb014e5.dll
PyGCGOpt.libs/libscip-a45274dafdb69da36fc7931381480703.dll
PyGCGOpt.libs/msvcp140-5a0264b714ebf5d957e6bf7dab3de583.dll
PyGCGOpt.libs/svml_dispmd-ffc3c8770debdabb377622d9ecf91d05.dll
