Metadata-Version: 2.1
Name: PyGCGOpt
Version: 0.4.0
Summary: Python interface and modeling environment for GCG
Home-page: https://github.com/scipopt/PyGCGOpt
Author: Lehrstuhl für Operations Research - RWTH Aachen University
Author-email: Lehrstuhl für Operations Research - RWTH Aachen University <gcg-bugs@or.rwth-aachen.de>
License: MIT
Project-URL: Homepage, https://github.com/SCIP-Interfaces/PyGCGOpt
Classifier: Development Status :: 2 - Pre-Alpha
Classifier: Intended Audience :: Science/Research
Classifier: Intended Audience :: Education
Classifier: License :: OSI Approved :: MIT License
Classifier: Programming Language :: Python :: 3
Classifier: Programming Language :: Cython
Classifier: Topic :: Scientific/Engineering :: Mathematics
Requires-Python: >=3.8
License-File: LICENSE
Requires-Dist: pyscipopt
